{
  "absensi": [
    {
      "id": 3,
      "nama": "Fajar Rizqy",
      "npm": "50420303",
      "pertemuan": "1",
      "keterangan": "Izin",
      "jam": "2"
    },
    {
      "id": 3,
      "nama": "Fajar Rizqy",
      "npm": "50420303",
      "pertemuan": "1",
      "keterangan": "Izin",
      "jam": "2"
    },
    {
      "id": 3,
      "nama": "Fajar Rizqy",
      "npm": "50420303",
      "pertemuan": "1",
      "keterangan": "Izin",
      "jam": "2"
    },
    {
      "id": 3,
      "nama": "Fajar Rizqy",
      "npm": "50420303",
      "pertemuan": "1",
      "keterangan": "Izin",
      "jam": "2"
    },
    {
      "id": 3,
      "nama": "Fajar Rizqy",
      "npm": "50420303",
      "pertemuan": "1",
      "keterangan": "Izin",
      "jam": "2"
    }
  ]
}